morelia/__init__.py
morelia/breadcrumbs.py
morelia/config.py
morelia/decorators.py
morelia/exceptions.py
morelia/formatters.py
morelia/grammar.py
morelia/i18n.py
morelia/matchers.py
morelia/parser.py
morelia/utils.py
morelia/visitors.py
morelia-0.10.1.dist-info/AUTHORS.rst
morelia-0.10.1.dist-info/LICENSE
morelia-0.10.1.dist-info/METADATA
morelia-0.10.1.dist-info/WHEEL
morelia-0.10.1.dist-info/RECORD
