Metadata-Version: 2.1
Name: morelia
Version: 0.10.1
Summary: for "Behavior Driven Development" (BDD) -- a client-facing scripting language to put the squeeze on all your features
Home-page: https://github.com/kidosoft/morelia
License: MIT
Keywords: test,bdd,behavior
Author: dryobates
Author-email: jakub.stolarski@gmail.com
Requires-Python: >=3.8,<4.0
Classifier: Development Status :: 4 - Beta
Classifier: Intended Audience :: Developers
Classifier: License :: OSI Approved :: MIT License
Classifier: Natural Language :: English
Classifier: Operating System :: OS Independent
Classifier: Programming Language :: Python :: 3
Classifier: Programming Language :: Python :: 3.8
Classifier: Programming Language :: Python :: 3.9
Classifier: Programming Language :: Python :: 3.10
Classifier: Programming Language :: Python :: 3.11
Classifier: Programming Language :: Python :: 3.12
Classifier: Topic :: Software Development :: Testing
Classifier: Topic :: Software Development :: Testing :: BDD
Requires-Dist: parse (>=1.12.0,<2.0.0)
Requires-Dist: requests (>=2.21,<3.0)
Requires-Dist: toml (>=0.10.0,<0.11.0)
Project-URL: Documentation, https://morelia.readthedocs.io/en/latest/
Project-URL: Repository, https://github.com/kidosoft/morelia
